asynctasq/__init__.py
asynctasq/__main__.py
asynctasq/cli/__init__.py
asynctasq/cli/commands/migrate.py
asynctasq/cli/commands/publish.py
asynctasq/cli/commands/worker.py
asynctasq/cli/config.py
asynctasq/cli/main.py
asynctasq/cli/parser.py
asynctasq/cli/utils.py
asynctasq/config.py
asynctasq/core/dispatcher.py
asynctasq/core/driver_factory.py
asynctasq/core/models.py
asynctasq/core/worker.py
asynctasq/drivers/__init__.py
asynctasq/drivers/base_driver.py
asynctasq/drivers/mysql_driver.py
asynctasq/drivers/postgres_driver.py
asynctasq/drivers/rabbitmq_driver.py
asynctasq/drivers/redis_driver.py
asynctasq/drivers/retry_utils.py
asynctasq/drivers/sqs_driver.py
asynctasq/integrations/fastapi.py
asynctasq/monitoring/__init__.py
asynctasq/monitoring/emitters.py
asynctasq/monitoring/monitoring.py
asynctasq/monitoring/registry.py
asynctasq/monitoring/types.py
asynctasq/py.typed
asynctasq/serializers/__init__.py
asynctasq/serializers/base_serializer.py
asynctasq/serializers/hooks/__init__.py
asynctasq/serializers/hooks/base.py
asynctasq/serializers/hooks/builtin.py
asynctasq/serializers/hooks/orm/__init__.py
asynctasq/serializers/hooks/orm/base.py
asynctasq/serializers/hooks/orm/django.py
asynctasq/serializers/hooks/orm/lazy_proxy.py
asynctasq/serializers/hooks/orm/lazy_proxy_hook.py
asynctasq/serializers/hooks/orm/sqlalchemy.py
asynctasq/serializers/hooks/orm/tortoise.py
asynctasq/serializers/msgspec_serializer.py
asynctasq/tasks/__init__.py
asynctasq/tasks/core/__init__.py
asynctasq/tasks/core/base_task.py
asynctasq/tasks/core/task_config.py
asynctasq/tasks/infrastructure/__init__.py
asynctasq/tasks/infrastructure/process_pool_manager.py
asynctasq/tasks/services/__init__.py
asynctasq/tasks/services/executor.py
asynctasq/tasks/services/function_resolver.py
asynctasq/tasks/services/repository.py
asynctasq/tasks/services/serializer.py
asynctasq/tasks/services/task_info_converter.py
asynctasq/tasks/types/__init__.py
asynctasq/tasks/types/async_process_task.py
asynctasq-1.6.0.dist-info/WHEEL
asynctasq-1.6.0.dist-info/entry_points.txt
asynctasq-1.6.0.dist-info/METADATA
asynctasq-1.6.0.dist-info/RECORD
