Metadata-Version: 2.3
Name: asynctasq
Version: 1.6.0
Summary: AsyncTasQ: A modern, async-first, type-safe task queue Python package inspired by Laravel. Runs on uvloop for maximum performance. Native FastAPI integration. Switch between multiple queue backends (Redis, PostgreSQL, MySQL, RabbitMQ, AWS SQS) with one config line. Automatic, smart ORM serialization (SQLAlchemy, Django, Tortoise) using msgpack reduces payloads by 90%+.
Keywords: queue,task,async,laravel,redis,sqs,background-tasks,worker,fastapi,sqlalchemy,django,tortoise-orm
Author: Adam Refaey
License: MIT
Classifier: Intended Audience :: Developers
Classifier: License :: OSI Approved :: MIT License
Classifier: Programming Language :: Python :: 3
Classifier: Programming Language :: Python :: 3.12
Classifier: Programming Language :: Python :: 3.13
Classifier: Programming Language :: Python :: 3.14
Classifier: Framework :: AsyncIO
Classifier: Topic :: Software Development :: Libraries :: Python Modules
Requires-Dist: msgspec>=0.18.0
Requires-Dist: pydantic-settings>=2.0.0
Requires-Dist: rich>=13.6.0
Requires-Dist: uvloop>=0.19.0
Requires-Dist: asynctasq[redis,sqs,postgres,mysql,rabbitmq,sqlalchemy,django,tortoise,fastapi,monitor] ; extra == 'all'
Requires-Dist: django>=5.0 ; extra == 'django'
Requires-Dist: psycopg2-binary>=2.9.9 ; extra == 'django'
Requires-Dist: fastapi>=0.109.0 ; extra == 'fastapi'
Requires-Dist: redis[hiredis]>=5.0.1 ; extra == 'monitor'
Requires-Dist: asyncmy>=0.2.9 ; extra == 'mysql'
Requires-Dist: cryptography>=41.0.5 ; extra == 'mysql'
Requires-Dist: asyncpg>=0.29.0 ; extra == 'postgres'
Requires-Dist: asyncpg-stubs>=0.29.0 ; extra == 'postgres'
Requires-Dist: aio-pika>=9.3.1 ; extra == 'rabbitmq'
Requires-Dist: redis[hiredis]>=5.0.1 ; extra == 'redis'
Requires-Dist: sqlalchemy>=2.0.22 ; extra == 'sqlalchemy'
Requires-Dist: greenlet>=3.0.0 ; extra == 'sqlalchemy'
Requires-Dist: aioboto3>=12.0.0 ; extra == 'sqs'
Requires-Dist: types-aioboto3[sqs]>=12.0.0 ; extra == 'sqs'
Requires-Dist: tortoise-orm>=0.21.0 ; extra == 'tortoise'
Requires-Python: >=3.12
Project-URL: Homepage, https://github.com/adamrefaey/asynctasq
Project-URL: Issues, https://github.com/adamrefaey/asynctasq/issues
Project-URL: Repository, https://github.com/adamrefaey/asynctasq
Provides-Extra: all
Provides-Extra: django
Provides-Extra: fastapi
Provides-Extra: monitor
Provides-Extra: mysql
Provides-Extra: postgres
Provides-Extra: rabbitmq
Provides-Extra: redis
Provides-Extra: sqlalchemy
Provides-Extra: sqs
Provides-Extra: tortoise
